<annotation>
	<folder>img</folder>
	<filename>61.jpg</filename>
	<path>D:\workspace\kaggle\HuBMAP\data\img\61.jpg</path>
	<source>
		<database>Unknown</database>
	</source>
	<size>
		<width>3000</width>
		<height>3000</height>
		<depth>3</depth>
	</size>
	<segmented>0</segmented>
	<object>
		<name>cell</name>
		<pose>Unspecified</pose>
		<truncated>1</truncated>
		<difficult>0</difficult>
		<bndbox>
			<xmin>182</xmin>
			<ymin>121</ymin>
			<xmax>2823</xmax>
			<ymax>3000</ymax>
		</bndbox>
	</object>
</annotation>
